mysqltsv/__init__.py
mysqltsv/errors.py
mysqltsv/functions.py
mysqltsv/reader.py
mysqltsv/row_type.py
mysqltsv/util.py
mysqltsv/writer.py
mysqltsv/tests/__init__.py
mysqltsv/tests/test_functions.py
mysqltsv/tests/test_reader.py
mysqltsv/tests/test_util.py
mysqltsv/tests/test_writer.py
mysqltsv-0.0.6.dist-info/DESCRIPTION.rst
mysqltsv-0.0.6.dist-info/METADATA
mysqltsv-0.0.6.dist-info/RECORD
mysqltsv-0.0.6.dist-info/WHEEL
mysqltsv-0.0.6.dist-info/metadata.json
mysqltsv-0.0.6.dist-info/top_level.txt
