Metadata-Version: 2.0
Name: mysqltsv
Version: 0.0.6
Summary: TSV Reader for the MySQL dialect.
Home-page: http://pypi.python.org/pypi/mysqltsv
Author: Aaron Halfaker
Author-email: aaron.halfaker@gmail.com
License: The MIT License (MIT)
